postgres_copy_binary/__init__.py
postgres_copy_binary-0.6.0.dist-info/METADATA
postgres_copy_binary-0.6.0.dist-info/WHEEL
postgres_copy_binary-0.6.0.dist-info/RECORD
