Metadata-Version: 2.1
Name: postgres-copy-binary
Version: 0.6.0
Summary: Provides a decoder for postgres COPY FROM WITH BINARY format that produces pyarrow / pandas / numpy / polars arrays.
Home-page: https://github.com/grihabor/postgres-copy-binary
License: MIT
Author: Gregory Borodin
Author-email: grihabor@gmail.com
Requires-Python: >=3.7
Classifier: License :: OSI Approved :: MIT License
Classifier: Programming Language :: Python :: 3
Classifier: Programming Language :: Python :: 3.7
Classifier: Programming Language :: Python :: 3.8
Classifier: Programming Language :: Python :: 3.9
Classifier: Programming Language :: Python :: 3.10
Classifier: Programming Language :: Python :: 3.11
Requires-Dist: postgres-copy-binary-extension-module (==0.6.0) ; python_version >= "3.7"
Project-URL: Repository, https://github.com/grihabor/postgres-copy-binary
